{"www.facebook.com": [{"pattern": "div._5pcp._5vsi > div > span:nth-child(1) > span > a:nth-child(2)", "numcompleted": 0, "id": "cdas0s", "completed_ids": []}], "www.reddit.com": [{"title": "DAE This old gem?", "pattern": "body > div.listing-chooser.initialized > div.contents > ul.other > li:nth-child(2) > a", "image": "https://files.helloben.co/upload/uploads/f545f0f24ea11d.jpg", "completed_ids": ["545ed114be616", "545ed114be616", "545ed114be616", "545ed114be616", "545ed114be616", "545ed114be616", "545ed114be616", "545ed114be616", "545edbd7b9cdd", "545edbd7b9cdd", "545edbd7b9cdd"], "desc": "Visit your saved posts", "id": "LY8FXD", "numcompleted": 11}, {"title": "Upboats!", "pattern": ".arrow.up", "image": "https://files.helloben.co/upload/uploads/f545f0f24ea11d.jpg", "completed_ids": ["545ed114be616", "545ed114be616", "545ed114be616", "545edbd7b9cdd", "545edbd7b9cdd", "545edbd7b9cdd", "545edbd7b9cdd", "545edbd7b9cdd", "545edbd7b9cdd", "545edbd7b9cdd", "545ed114be616", "545ed114be616", "545ed114be616", "545edbd7b9cdd", "545edbd7b9cdd", "545edbd7b9cdd", "545edbd7b9cdd", "545edbd7b9cdd", "545edbd7b9cdd", "545edbd7b9cdd", "545edbd7b9cdd", "545edbd7b9cdd", "545ed114be616", "545edbd7b9cdd", "545edbd7b9cdd", "545edbd7b9cdd", "545edbd7b9cdd", "545edbd7b9cdd"], "desc": "You've upvoted a post!", "id": "9KSCBF", "numcompleted": 28}, {"title": "Boo! Get off the front page!", "pattern": ".arrow.down", "image": "https://files.helloben.co/upload/uploads/f545f0f24ea11d.jpg", "completed_ids": ["545ed114be616", "545ed114be616", "545edbd7b9cdd", "545ed114be616", "545ed114be616", "545ed114be616", "545ed114be616", "545edbd7b9cdd", "545edbd7b9cdd", "545edbd7b9cdd", "545edbd7b9cdd", "545edbd7b9cdd", "545edbd7b9cdd"], "desc": "You've displayed your hatred of a post by downvoting it.", "id": "C80M7L", "numcompleted": 13}], "www.twitter.com": [{"title": "Recycling!", "pattern": "#stream-item-tweet-531438294773428224 > div > div.content > div.stream-item-footer > div > div.ProfileTweet-action.ProfileTweet-action--retweet.js-toggleState.js-toggleRt > button.ProfileTweet-actionButton.js-actionButton.js-actionRetweet.js-tooltip", "image": "https://g.twimg.com/Twitter_logo_blue.png", "completed_ids": [], "desc": "Retweet a Tweet.", "id": "AFKG0K", "numcompleted": 0}, {"title": "Recycling!", "pattern": "#retweet-tweet-dialog-dialog > div.modal-content > div.modal-footer > button.btn.primary-btn.retweet-action", "image": "https://g.twimg.com/Twitter_logo_blue.png", "completed_ids": [], "numcompleted": 0, "id": "BMSO2I", "desc": "Retweet a Tweet."}], "twitter.com": [{"title": "140 characters and counting", "pattern": "#timeline > div.timeline-tweet-box > div > form > div.toolbar.js-toolbar > div.tweet-button > button", "image": "https://files.helloben.co/upload/uploads/f545f30fe64f16.jpg", "completed_ids": ["545ed114be616", "545ed114be616", "545ed114be616", "545ed114be616", "545edbd7b9cdd", "545edbd7b9cdd", "545ed114be616", "545edbd7b9cdd", "545edbd7b9cdd", "545ed114be616", "545edbd7b9cdd", "545ed114be616"], "numcompleted": 12, "id": "AOJWZ5", "desc": "Create a tweet"}, {"title": "Begone, foul Tweet!", "pattern": ".btn.primary-btn.delete-action", "image": "https://files.helloben.co/upload/uploads/f545f30fe64f16.jpg", "completed_ids": ["545ed114be616"], "desc": "You have banished a tweet to the underworld.", "id": "0JBMWM", "numcompleted": 1}], "echo.newtechnetwork.org": [{"title": "Goin' to class!", "pattern": "div.title-row > h2 > a", "image": "https://files.helloben.co/upload/uploads/f545f20f28ad8a.jpg", "completed_ids": ["545e98db92d69", "545e98db92d69", "545edbd7b9cdd", "545edbd7b9cdd", "545edbd7b9cdd", "545edbd7b9cdd", "545edbd7b9cdd", "545edbd7b9cdd", "545edbd7b9cdd", "545edbd7b9cdd", "545edbd7b9cdd", "545edbd7b9cdd", "545edbd7b9cdd", "545edbd7b9cdd", "545edbd7b9cdd", "545edbd7b9cdd", "545edbd7b9cdd", "545edbd7b9cdd", "545edbd7b9cdd", "545ed114be616", "545edbd7b9cdd", "545edbd7b9cdd", "545edbd7b9cdd"], "numcompleted": 23, "id": "sfkns", "desc": "Visit a class page"}, {"title": "How are you doing?", "pattern": "body > header > div > div > ul.nav.header-nav.main.list-inline.col-xs-8 > li.dropdown.block-nav.main-nav > div > div > div:nth-child(3) > a", "completed_ids": [], "numcompleted": 0, "id": "lfjbs", "desc": "Visit your grades page"}, {"title": "Like'd!", "pattern": "div.AgendaAction > span > a > img", "image": "https://files.helloben.co/upload/uploads/f545f20f28ad8a.jpg", "completed_ids": ["545e98db92d69", "545eca239c665", "545edbd7b9cdd", "545edbd7b9cdd", "545edbd7b9cdd", "545edbd7b9cdd", "545edbd7b9cdd", "545edbd7b9cdd", "545edbd7b9cdd", "545edbd7b9cdd", "545edbd7b9cdd", "545edbd7b9cdd", "545edbd7b9cdd", "545edbd7b9cdd", "545edbd7b9cdd", "545edbd7b9cdd", "545edbd7b9cdd", "545edbd7b9cdd", "545edbd7b9cdd", "545edbd7b9cdd", "545edbd7b9cdd", "545edbd7b9cdd", "545edbd7b9cdd", "545edbd7b9cdd", "545edbd7b9cdd", "545edbd7b9cdd", "545edbd7b9cdd", "545edbd7b9cdd", "545ed114be616", "545ed114be616", "545ed114be616", "545ed114be616", "545ed114be616", "545ed114be616", "545ed114be616", "545ed114be616", "545ed114be616", "545ed114be616", "545ed114be616", "545edbd7b9cdd", "545ed114be616", "545ed114be616", "545ed114be616", "545ed114be616"], "desc": "I think I like you!", "id": "fljndl", "numcompleted": 44}], "github.com": [{"title": "The Open Sauce", "pattern": ".button.primary.first-in-line", "image": "https://files.helloben.co/upload/uploads/f545f74236b6b8.png", "completed_ids": ["545ed114be616", "545edbd7b9cdd"], "desc": "Created and GitHub Repo in an attempt to share your code with the world!", "id": "KYGBQ0", "numcompleted": 2}, {"title": "Sparkling Star!", "pattern": ".minibutton.with-count.js-toggler-target.star-button", "image": "https://files.helloben.co/upload/uploads/f545f74236b6b8.png", "completed_ids": ["545ed114be616", "545ed114be616", "545edbd7b9cdd"], "numcompleted": 3, "id": "H67AGI", "desc": "You have stared a repository on GitHub! Twinkle Twinkle!"}]}